plan_d/__init__.py
plan_d/__main__.py
plan_d/_internal/__init__.py
plan_d/_internal/api.py
plan_d/_internal/debugger.py
plan_d/_internal/utils.py
plan_d-0.2.4.dist-info/LICENSE
plan_d-0.2.4.dist-info/METADATA
plan_d-0.2.4.dist-info/WHEEL
plan_d-0.2.4.dist-info/entry_points.txt
plan_d-0.2.4.dist-info/RECORD
